src/async_modbus_scanner.py
src/modbus_scanner.py
modbus_scanner-1.0.2.dist-info/LICENSE
modbus_scanner-1.0.2.dist-info/METADATA
modbus_scanner-1.0.2.dist-info/WHEEL
modbus_scanner-1.0.2.dist-info/top_level.txt
modbus_scanner-1.0.2.dist-info/RECORD
