Metadata-Version: 2.1
Name: modbus-scanner
Version: 1.0.2
Summary: Scanner For Modbus RTU and TCP/IP
Author-email: Karmavir Joshi <karmavirj@protonmail.com>
Project-URL: Homepage, https://github.com/kvjoshi/modbus_scanner
Project-URL: Issues, https://github.com/kvjoshi/modbus_scanner/issues
Classifier: Programming Language :: Python :: 3
Classifier: License :: OSI Approved :: MIT License
Classifier: Operating System :: OS Independent
Requires-Python: >=3.8
License-File: LICENSE
